jaxite/__init__.py
jaxite/jaxite_bool/__init__.py
jaxite/jaxite_bool/bool_encoding.py
jaxite/jaxite_bool/bool_params.py
jaxite/jaxite_bool/jaxite_bool.py
jaxite/jaxite_bool/jaxite_bool_multigate_test.py
jaxite/jaxite_bool/jaxite_bool_test.py
jaxite/jaxite_bool/lut.py
jaxite/jaxite_bool/lut_test.py
jaxite/jaxite_bool/pmap_test.py
jaxite/jaxite_bool/type_converters.py
jaxite/jaxite_lib/__init__.py
jaxite/jaxite_lib/blind_rotate_test.py
jaxite/jaxite_lib/bootstrap.py
jaxite/jaxite_lib/bootstrap_test.py
jaxite/jaxite_lib/decomposition.py
jaxite/jaxite_lib/decomposition_test.py
jaxite/jaxite_lib/encoding.py
jaxite/jaxite_lib/encoding_test.py
jaxite/jaxite_lib/jax_helpers.py
jaxite/jaxite_lib/key_switch.py
jaxite/jaxite_lib/key_switch_test.py
jaxite/jaxite_lib/lwe.py
jaxite/jaxite_lib/lwe_test.py
jaxite/jaxite_lib/matrix_utils.py
jaxite/jaxite_lib/matrix_utils_test.py
jaxite/jaxite_lib/parameters.py
jaxite/jaxite_lib/polymul_kernel.py
jaxite/jaxite_lib/polymul_kernel_test.py
jaxite/jaxite_lib/random_source.py
jaxite/jaxite_lib/random_source_test.py
jaxite/jaxite_lib/rgsw.py
jaxite/jaxite_lib/rgsw_test.py
jaxite/jaxite_lib/rlwe.py
jaxite/jaxite_lib/rlwe_test.py
jaxite/jaxite_lib/test_polynomial.py
jaxite/jaxite_lib/test_polynomial_test.py
jaxite/jaxite_lib/test_utils.py
jaxite/jaxite_lib/types.py
jaxite-0.0.3.dist-info/METADATA
jaxite-0.0.3.dist-info/WHEEL
jaxite-0.0.3.dist-info/licenses/LICENSE
jaxite-0.0.3.dist-info/RECORD
