Metadata-Version: 2.3
Name: jaxite
Version: 0.0.3
Summary: A Homomorphic Encryption implementation (CGGI) written in JAX
Project-URL: Documentation, https://github.com/google/jaxite
Project-URL: Issues, https://github.com/google/jaxite/issues
Project-URL: Source, https://github.com/google/jaxite
Author: Asra Ali, Cathie Yun, Jeremy Kun, Shruthi Gorantala
License: MIT
Classifier: Development Status :: 4 - Beta
Classifier: Programming Language :: Python
Classifier: Programming Language :: Python :: 3.7
Classifier: Programming Language :: Python :: 3.8
Classifier: Programming Language :: Python :: 3.9
Classifier: Programming Language :: Python :: 3.10
Classifier: Programming Language :: Python :: 3.11
Classifier: Programming Language :: Python :: Implementation :: CPython
Classifier: Programming Language :: Python :: Implementation :: PyPy
Requires-Python: >=3.7
Requires-Dist: jaxlib~=0.4.13
Requires-Dist: jax~=0.4.13
